nefnir/__init__.py
nefnir/__main__.py
nefnir/nefnir.py
nefnir/rules.json
nefnir/tags.json
nefnir/wrapper.py
nefnir-1.0.2.dist-info/LICENSE
nefnir-1.0.2.dist-info/METADATA
nefnir-1.0.2.dist-info/WHEEL
nefnir-1.0.2.dist-info/top_level.txt
nefnir-1.0.2.dist-info/RECORD
