Metadata-Version: 2.1
Name: nefnir
Version: 1.0.2
Summary: A lemmatizer for Icelandic text
Home-page: https://github.com/sverrirab/nefnir-package
Author: Sverrir Á. Berg
Author-email: sab@keilir.com
License: Apache Software License 2.0
Keywords: nefnir
Platform: UNKNOWN
Classifier: Development Status :: 3 - Alpha
Classifier: Intended Audience :: Developers
Classifier: License :: OSI Approved :: Apache Software License
Classifier: Natural Language :: Icelandic
Classifier: Programming Language :: Python :: 3
Classifier: Programming Language :: Python :: 3.6
Classifier: Programming Language :: Python :: 3.7
Requires-Python: >=3.6
